aadiscordmultiverse/__init__.py
aadiscordmultiverse/admin.py
aadiscordmultiverse/app_settings.py
aadiscordmultiverse/apps.py
aadiscordmultiverse/auth_hooks.py
aadiscordmultiverse/managers.py
aadiscordmultiverse/models.py
aadiscordmultiverse/signals.py
aadiscordmultiverse/tasks.py
aadiscordmultiverse/urls.py
aadiscordmultiverse/utils.py
aadiscordmultiverse/views.py
aadiscordmultiverse/discord_client/__init__.py
aadiscordmultiverse/discord_client/app_settings.py
aadiscordmultiverse/discord_client/client.py
aadiscordmultiverse/discord_client/exceptions.py
aadiscordmultiverse/discord_client/helpers.py
aadiscordmultiverse/discord_client/tests/__init__.py
aadiscordmultiverse/discord_client/tests/piloting_concurrency.py
aadiscordmultiverse/discord_client/tests/piloting_functionality.py
aadiscordmultiverse/discord_client/tests/rate_limits.md
aadiscordmultiverse/discord_client/tests/test_client.py
aadiscordmultiverse/discord_client/tests/test_exceptions.py
aadiscordmultiverse/discord_client/tests/test_helpers.py
aadiscordmultiverse/locale/en/LC_MESSAGES/django.po
aadiscordmultiverse/management/commands/__init.py
aadiscordmultiverse/management/commands/dmv_core_to_dmv.py
aadiscordmultiverse/migrations/0001_initial.py
aadiscordmultiverse/migrations/0002_discordmanagedserver_alliance_access_and_more.py
aadiscordmultiverse/migrations/0003_alter_discordmanagedserver_options.py
aadiscordmultiverse/migrations/0004_discordmanagedserver_ignored_groups.py
aadiscordmultiverse/migrations/0005_discordmanagedserver_include_all_managed_groups_and_more.py
aadiscordmultiverse/migrations/0006_sync_groups_to_new_models.py
aadiscordmultiverse/migrations/0007_remove_discordmanagedserver_ignored_groups.py
aadiscordmultiverse/migrations/0008_serveractivefilter.py
aadiscordmultiverse/migrations/__init__.py
aadiscordmultiverse/templates/aadiscordmultiverse/dmv_service_ctrl.html
aadiscordmultiverse/templates/aadiscordmultiverse/dmv_service_ctrl_bs5.html
aadiscordmultiverse/tests/__init__.py
allianceauth_discord_multiverse-0.0.1b3.dist-info/licenses/LICENSE
allianceauth_discord_multiverse-0.0.1b3.dist-info/WHEEL
allianceauth_discord_multiverse-0.0.1b3.dist-info/METADATA
allianceauth_discord_multiverse-0.0.1b3.dist-info/RECORD
