Metadata-Version: 2.4
Name: allianceauth-discord-multiverse
Version: 0.0.1b3
Summary: Service module for managing an unlimited number of discord servers from a single auth instance. It can run side by side with the core auth discord service, or completely standalone.
Keywords: allianceauth,eveonline
Author-email: AaronKable <aaronkable@gmail.com>
Requires-Python: >=3.8
Classifier: Environment :: Web Environment
Classifier: Framework :: Celery
Classifier: Framework :: Django
Classifier: Framework :: Django :: 4.0
Classifier: Framework :: Django :: 4.2
Classifier: Intended Audience :: Developers
Classifier: License :: OSI Approved :: MIT License
Classifier: Operating System :: OS Independent
Classifier: Programming Language :: Python
Classifier: Programming Language :: Python :: 3 :: Only
Classifier: Programming Language :: Python :: 3.8
Classifier: Programming Language :: Python :: 3.9
Classifier: Programming Language :: Python :: 3.10
Classifier: Programming Language :: Python :: 3.11
Classifier: Programming Language :: Python :: 3.12
Classifier: Programming Language :: Python :: Implementation :: CPython
Classifier: Topic :: Internet :: WWW/HTTP
Classifier: Topic :: Internet :: WWW/HTTP :: Dynamic Content
License-File: LICENSE
Requires-Dist: allianceauth<5,>=3
Requires-Dist: allianceauth-securegroups ; extra == "test"
Requires-Dist: requests-mock ; extra == "test"
Project-URL: Homepage, https://github.com/Solar-Helix-Independent-Transport/allianceauth-discord-multiverse
Project-URL: Source, https://github.com/Solar-Helix-Independent-Transport/allianceauth-discord-multiverse
Project-URL: Tracker, https://github.com/Solar-Helix-Independent-Transport/allianceauth-discord-multiverse/issues
Provides-Extra: test
